shadow_writer/agents/editor.py
shadow_writer/agents/researcher.py
shadow_writer/agents/writer.py
shadow_writer/llm/gemini.py
shadow_writer/llm/openai.py
shadow_writer/models/api.py
shadow_writer/rag/tidb.py
shadow_writer/server/main.py
shadow_writer-0.0.2.dist-info/LICENSE
shadow_writer-0.0.2.dist-info/METADATA
shadow_writer-0.0.2.dist-info/WHEEL
shadow_writer-0.0.2.dist-info/RECORD
