Metadata-Version: 2.1
Name: shadow-writer
Version: 0.0.2
Summary: 
License: Apache-2.0 license
Author: IANTHEREAL
Author-email: argregoryian@gmail.com
Requires-Python: >=3.9,<4.0
Classifier: License :: Other/Proprietary License
Classifier: Programming Language :: Python :: 3
Classifier: Programming Language :: Python :: 3.9
Classifier: Programming Language :: Python :: 3.10
Classifier: Programming Language :: Python :: 3.11
Classifier: Programming Language :: Python :: 3.12
Requires-Dist: fastapi (>=0.110.1,<0.111.0)
Requires-Dist: google-generativeai (>=0.5.0,<0.6.0)
Requires-Dist: openai (>=1.17.1,<2.0.0)
Requires-Dist: pandas (>=2.2.2,<3.0.0)
Requires-Dist: pydantic (>=2.7.0,<3.0.0)
Requires-Dist: pymysql (>=1.1.0,<2.0.0)
Requires-Dist: python-dotenv (>=1.0.1,<2.0.0)
Requires-Dist: sqlalchemy (>=2.0.29,<3.0.0)
Requires-Dist: tiktoken (>=0.6.0,<0.7.0)
Requires-Dist: uvicorn (>=0.29.0,<0.30.0)
